{
  "Top": "fir",
  "RtlTop": "fir",
  "RtlPrefix": "",
  "SourceLanguage": "cpp",
  "ResetStyle": "control",
  "GenerateBdFiles": "0",
  "HostMachineBits": "64",
  "Target": {
    "Family": "zynq",
    "Device": "xc7z020",
    "Package": "-clg484",
    "Speed": "-1"
  },
  "HlsSolution": {"Config": [
      "config_sdx -target=none",
      "config_export -vivado_optimization_level=2",
      "config_export -vivado_phys_opt=place",
      "config_export -vivado_report_level=0"
    ]},
  "Args": {
    "output": {
      "index": "0",
      "type": {
        "kinds": ["pointer"],
        "dataType": "int",
        "dataWidth": "32",
        "interfaceRef": "output_r"
      }
    },
    "input": {
      "index": "1",
      "type": {
        "dataType": "int",
        "dataWidth": "32",
        "interfaceRef": "input_r"
      }
    }
  },
  "Return": {
    
  },
  "ClockInfo": {
    "ClockName": "ap_clk",
    "ClockPeriod": "10",
    "IsCombLogic": "0",
    "II": "x",
    "Latency": "13",
    "Uncertainty": "1.25"
  },
  "Xdc": {"OocClocks": ["create_clock -name ap_clk -period 10.000 [get_ports ap_clk]"]},
  "Ipx": {
    "Vendor": "xilinx.com",
    "Library": "hls",
    "Name": "fir",
    "Version": "1.0",
    "DisplayName": "Fir",
    "Revision": "",
    "Description": "An IP generated by Vivado HLS",
    "Taxonomy": "\/VIVADO_HLS_IP",
    "AutoFamilySupport": ""
  },
  "Files": {
    "CSource": ["..\/fir_symmetry_optim.cpp"],
    "Vhdl": [
      "impl\/vhdl\/fir_c1.vhd",
      "impl\/vhdl\/fir_shift_reg.vhd",
      "impl\/vhdl\/fir.vhd"
    ],
    "Verilog": [
      "impl\/verilog\/fir_c1.v",
      "impl\/verilog\/fir_c1_rom.dat",
      "impl\/verilog\/fir_shift_reg.v",
      "impl\/verilog\/fir_shift_reg_ram.dat",
      "impl\/verilog\/fir.v"
    ],
    "Misc": ["impl\/misc\/logo.png"],
    "DesignXml": "C:\/Users\/Riya_Sachdeva\/Desktop\/FIR_Filter_2\/solution1\/.autopilot\/db\/fir.design.xml",
    "DebugDir": "C:\/Users\/Riya_Sachdeva\/Desktop\/FIR_Filter_2\/solution1\/.debug",
    "ProtoInst": ["C:\/Users\/Riya_Sachdeva\/Desktop\/FIR_Filter_2\/solution1\/.debug\/fir.protoinst"]
  },
  "SubcoreInfo": {
    "HasXpmMemory": false,
    "HasClockedDsp": false,
    "IP": []
  },
  "Interfaces": {
    "ap_clk": {
      "type": "clock",
      "ctype": {"CLK": {"Type": "bool"}},
      "bundle_name": "ap_clk",
      "bundle_role": "default",
      "reset": "ap_rst"
    },
    "ap_ctrl": {
      "type": "ap_ctrl",
      "ctrl_ports": "ap_start ap_done ap_idle ap_ready",
      "ctype": {
        "start": {"Type": "bool"},
        "done": {"Type": "bool"},
        "idle": {"Type": "bool"},
        "ready": {"Type": "bool"}
      }
    },
    "ap_rst": {
      "type": "reset",
      "polarity": "ACTIVE_HIGH",
      "ctype": {"RST": {"Type": "bool"}},
      "bundle_name": "ap_rst",
      "bundle_role": "default"
    },
    "input_r": {
      "type": "data",
      "dir": "in",
      "width": "32",
      "ctype": {"DATA": {
          "Type": "integer signed",
          "Width": "32"
        }},
      "bundle_name": "input_r",
      "bundle_role": "default"
    },
    "output_r": {
      "type": "data",
      "dir": "out",
      "width": "32",
      "ctype": {"DATA": {
          "Type": "integer signed",
          "Width": "32"
        }},
      "bundle_name": "output_r",
      "bundle_role": "default"
    }
  },
  "RtlPorts": {
    "ap_clk": {
      "dir": "in",
      "width": "1"
    },
    "ap_rst": {
      "dir": "in",
      "width": "1"
    },
    "ap_start": {
      "dir": "in",
      "width": "1"
    },
    "ap_done": {
      "dir": "out",
      "width": "1"
    },
    "ap_idle": {
      "dir": "out",
      "width": "1"
    },
    "ap_ready": {
      "dir": "out",
      "width": "1"
    },
    "output_r": {
      "dir": "out",
      "width": "32"
    },
    "output_r_ap_vld": {
      "dir": "out",
      "width": "1"
    },
    "input_r": {
      "dir": "in",
      "width": "32"
    }
  },
  "ModuleInfo": {
    "Hierarchy": {"ModuleName": "fir"},
    "Info": {"fir": {
        "FunctionProtocol": "ap_ctrl_hs",
        "isTaskLevelControl": "1",
        "isPipelined": "0",
        "isCombinational": "0",
        "isOneStateSeq": "0"
      }},
    "Metrics": {"fir": {
        "Latency": {
          "LatencyBest": "13",
          "LatencyAvg": "19",
          "LatencyWorst": "25",
          "PipelineIIMin": "14",
          "PipelineIIMax": "26",
          "PipelineII": "14 ~ 26",
          "PipelineDepth": "",
          "PipelineType": "none"
        },
        "Timing": {
          "Target": "10.00",
          "Uncertainty": "1.25",
          "Estimate": "8.510"
        },
        "Loops": [{
            "Name": "Shift_Accum_Loop",
            "TripCount": "6",
            "LatencyMin": "12",
            "LatencyMax": "24",
            "Latency": "12 ~ 24",
            "PipelineII": "",
            "PipelineDepthMin": "2",
            "PipelineDepthMax": "4",
            "PipelineDepth": "2 ~ 4"
          }],
        "Area": {
          "BRAM_18K": "0",
          "DSP48E": "4",
          "FF": "286",
          "LUT": "225",
          "URAM": "0"
        }
      }}
  },
  "Sdx": {
    "Target": "none",
    "ProfileOption": "0",
    "ProfileType": "none",
    "XO": "",
    "KernelName": "fir",
    "EnableXoSwEmu": "1"
  },
  "GenData": {
    "DataVersion": "0.2",
    "Time": "2023-12-13 19:24:38 +0530",
    "ToolName": "vivado_hls",
    "ToolVersion": "2019.1"
  }
}
